shapely/__init__.py
shapely/_buildcfg.py
shapely/_geos.pxi
shapely/affinity.py
shapely/coords.py
shapely/ctypes_declarations.py
shapely/errors.py
shapely/geos.py
shapely/impl.py
shapely/iterops.py
shapely/linref.py
shapely/ops.py
shapely/predicates.py
shapely/prepared.py
shapely/strtree.py
shapely/topology.py
shapely/validation.py
shapely/wkb.py
shapely/wkt.py
shapely/algorithms/__init__.py
shapely/algorithms/cga.py
shapely/algorithms/polylabel.py
shapely/examples/__init__.py
shapely/examples/dissolve.py
shapely/examples/geoms.py
shapely/examples/intersect.py
shapely/geometry/__init__.py
shapely/geometry/base.py
shapely/geometry/collection.py
shapely/geometry/conftest.py
shapely/geometry/geo.py
shapely/geometry/linestring.py
shapely/geometry/multilinestring.py
shapely/geometry/multipoint.py
shapely/geometry/multipolygon.py
shapely/geometry/point.py
shapely/geometry/polygon.py
shapely/geometry/proxy.py
shapely/speedups/__init__.py
shapely/speedups/_speedups.c
shapely/speedups/_speedups.pyx
shapely/vectorized/__init__.py
shapely/vectorized/_vectorized.pyx
Shapely_cellvit-1.8.5.post1.dist-info/LICENSE.txt
Shapely_cellvit-1.8.5.post1.dist-info/METADATA
Shapely_cellvit-1.8.5.post1.dist-info/WHEEL
Shapely_cellvit-1.8.5.post1.dist-info/top_level.txt
Shapely_cellvit-1.8.5.post1.dist-info/RECORD
