Metadata-Version: 2.1
Name: Shapely-cellvit
Version: 1.8.5.post1
Summary: Geometric objects, predicates, and operations
Home-page: https://github.com/shapely/shapely
Author: Sean Gillies
Author-email: sean.gillies@gmail.com
Maintainer: Sean Gillies
Maintainer-email: sean.gillies@gmail.com
License: BSD
Keywords: geometry topology gis
Platform: UNKNOWN
Classifier: Development Status :: 5 - Production/Stable
Classifier: Intended Audience :: Developers
Classifier: Intended Audience :: Science/Research
Classifier: License :: OSI Approved :: BSD License
Classifier: Operating System :: OS Independent
Classifier: Programming Language :: Python :: 3
Classifier: Programming Language :: Python :: 3.6
Classifier: Programming Language :: Python :: 3.7
Classifier: Programming Language :: Python :: 3.8
Classifier: Programming Language :: Python :: 3.9
Classifier: Programming Language :: Python :: 3.10
Classifier: Topic :: Scientific/Engineering :: GIS
Requires-Python: >=3.6
License-File: LICENSE.txt
Provides-Extra: all
Requires-Dist: pytest ; extra == 'all'
Requires-Dist: pytest-cov ; extra == 'all'
Requires-Dist: numpy ; extra == 'all'
Provides-Extra: test
Requires-Dist: pytest ; extra == 'test'
Requires-Dist: pytest-cov ; extra == 'test'
Provides-Extra: vectorized
Requires-Dist: numpy ; extra == 'vectorized'
